regime_switch_model/__init__.py
regime_switch_model/rshmm.py
regime_switch_model/utils.py
regime_switch_model-0.1.1.dist-info/DESCRIPTION.rst
regime_switch_model-0.1.1.dist-info/METADATA
regime_switch_model-0.1.1.dist-info/RECORD
regime_switch_model-0.1.1.dist-info/WHEEL
regime_switch_model-0.1.1.dist-info/metadata.json
regime_switch_model-0.1.1.dist-info/top_level.txt
