Metadata-Version: 2.0
Name: regime-switch-model
Version: 0.1.1
Summary: Regime-Switching Model
Home-page: https://github.com/Liuyi-Hu/regime_switch_model
Author: Liuyi Hu
Author-email: liuyi.hu.apply@gmail.com
License: new BSD
Platform: UNKNOWN
Classifier: Development Status :: 3 - Alpha
Classifier: License :: OSI Approved
Classifier: Programming Language :: Python :: 2.7
Classifier: Topic :: Scientific/Engineering
Requires-Dist: numpy
Requires-Dist: scikit-learn
Requires-Dist: scipy
